<?xml version="1.0"?>
<opencv_storage>
<stage14>
  <maxWeakCount>14</maxWeakCount>
  <stageThreshold>-2.2878818213939667e-01</stageThreshold>
  <weakClassifiers>
    <_>
      <internalNodes>
        0 -1 3792883 4.2168825166299939e-04</internalNodes>
      <leafValues>
        9.0147548913955688e-01 -7.9166668653488159e-01</leafValues></_>
    <_>
      <internalNodes>
        0 -1 188377 1.9331043586134911e-04</internalNodes>
      <leafValues>
        -1.6056172549724579e-01 7.6042783260345459e-01</leafValues></_>
    <_>
      <internalNodes>
        0 -1 172539 3.7157889455556870e-03</internalNodes>
      <leafValues>
        -2.6573762297630310e-01 6.1050951480865479e-01</leafValues></_>
    <_>
      <internalNodes>
        0 -1 730133 1.2578361202031374e-04</internalNodes>
      <leafValues>
        3.0459341406822205e-01 -6.4869272708892822e-01</leafValues></_>
    <_>
      <internalNodes>
        0 -1 3124265 1.3267463073134422e-03</internalNodes>
      <leafValues>
        -3.4812110662460327e-01 5.4771333932876587e-01</leafValues></_>
    <_>
      <internalNodes>
        0 -1 3988092 5.8262969832867384e-04</internalNodes>
      <leafValues>
        -3.5700353980064392e-01 4.5103377103805542e-01</leafValues></_>
    <_>
      <internalNodes>
        0 -1 4888719 -6.0452627949416637e-03</internalNodes>
      <leafValues>
        5.7523107528686523e-01 -2.6272630691528320e-01</leafValues></_>
    <_>
      <internalNodes>
        0 -1 5776000 -7.8048789873719215e-05</internalNodes>
      <leafValues>
        -7.0985567569732666e-01 2.2900098562240601e-01</leafValues></_>
    <_>
      <internalNodes>
        0 -1 27751 -5.1255859434604645e-03</internalNodes>
      <leafValues>
        6.5954446792602539e-01 -2.7090343832969666e-01</leafValues></_>
    <_>
      <internalNodes>
        0 -1 2980946 -3.9416534127667546e-04</internalNodes>
      <leafValues>
        -7.8968322277069092e-01 2.1208894252777100e-01</leafValues></_>
    <_>
      <internalNodes>
        0 -1 172302 -4.2215210851281881e-04</internalNodes>
      <leafValues>
        5.9281998872756958e-01 -2.7784889936447144e-01</leafValues></_>
    <_>
      <internalNodes>
        0 -1 184439 9.6152172773145139e-05</internalNodes>
      <leafValues>
        -3.0265933275222778e-01 5.1918095350265503e-01</leafValues></_>
    <_>
      <internalNodes>
        0 -1 3793255 3.5402760840952396e-03</internalNodes>
      <leafValues>
        1.6990497708320618e-01 -9.4488841295242310e-01</leafValues></_>
    <_>
      <internalNodes>
        0 -1 932118 -1.2910511577501893e-03</internalNodes>
      <leafValues>
        4.1314655542373657e-01 -3.9253869652748108e-01</leafValues></_></weakClassifiers></stage14>
</opencv_storage>
